uenp/__init__.py
uenp/algebra_linear.py
uenp-0.0.1.dist-info/LICENSE
uenp-0.0.1.dist-info/METADATA
uenp-0.0.1.dist-info/WHEEL
uenp-0.0.1.dist-info/top_level.txt
uenp-0.0.1.dist-info/RECORD
