Metadata-Version: 2.1
Name: uenp
Version: 0.0.1
Summary: UENP official library package
Author-email: Henrique GC <henriq4net@gmail.com>
Project-URL: Homepage, https://github.com/henriq4/uenp_lib
Project-URL: Bug Tracker, https://github.com/henriq4/uenp_lib/issues
Classifier: Programming Language :: Python :: 3
Classifier: License :: OSI Approved :: GNU General Public License v3 (GPLv3)
Classifier: Operating System :: OS Independent
Requires-Python: >=3.7
License-File: LICENSE
